imschrm/__init__.py
imschrm/_gcpy_codepoints.py
imschrm/cli.py
imschrm/codepoint_sets.py
imschrm/doc_sequence.py
imschrm/hrm.py
imschrm-1.1.0.dist-info/LICENSE.txt
imschrm-1.1.0.dist-info/METADATA
imschrm-1.1.0.dist-info/WHEEL
imschrm-1.1.0.dist-info/entry_points.txt
imschrm-1.1.0.dist-info/top_level.txt
imschrm-1.1.0.dist-info/RECORD
