Metadata-Version: 2.1
Name: imschrm
Version: 1.1.0
Summary: Validates IMSC documents against the IMSC HRM
Home-page: https://www.sandflow.com
Author: Sandflow Consulting LLC
Author-email: info@sandflow.com
Project-URL: Bug Reports, https://github.com/sandflow/imscHRM/issues
Project-URL: Source, https://github.com/sandflow/imscHRM
Keywords: ttml,imsc,smpte-tt,hrm,complexity
Classifier: Development Status :: 4 - Beta
Classifier: Intended Audience :: Developers
Classifier: Topic :: Software Development :: Build Tools
Classifier: Environment :: Console
Classifier: License :: OSI Approved :: BSD License
Classifier: Programming Language :: Python :: 3.7
Classifier: Programming Language :: Python :: 3.8
Classifier: Programming Language :: Python :: 3 :: Only
Classifier: Topic :: Multimedia
Requires-Python: >=3.8, <4
License-File: LICENSE.txt
Requires-Dist: ttconv >=1.1.0
